embedin/__init__.py
embedin/client/__init__.py
embedin/embedding/__init__.py
embedin/embedding/embedding_base.py
embedin/embedding/openai_embedding.py
embedin/embedding/sentence_transformer.py
embedin/index/__init__.py
embedin/index/faiss.py
embedin/index/flat_index.py
embedin/index/hnsw_index.py
embedin/index/hnswlib.py
embedin/index/index_base.py
embedin/model/__init__.py
embedin/model/collection_model.py
embedin/model/embedding_model.py
embedin/repository/__init__.py
embedin/repository/collection_repository.py
embedin/repository/embedding_repository.py
embedin/service/__init__.py
embedin/service/collection_service.py
embedin/service/embedding_service.py
embedin/util/__init__.py
tests/client/__init__.py
tests/embedding/__init__.py
tests/embedding/test_embedding.py
tests/embedding/test_embedding_base.py
tests/embedding/test_openai_embedding.py
tests/embedding/test_sentence_transformer_embedding.py
tests/index/__init__.py
tests/index/test_faiss.py
tests/index/test_flat_index.py
tests/index/test_hnsw_index.py
tests/index/test_hnswlib.py
tests/model/__init__.py
tests/model/test_collection_model.py
tests/model/test_embedding_model.py
tests/repository/__init__.py
tests/repository/test_collection_repository.py
tests/repository/test_embedding_repository.py
tests/service/__init__.py
tests/service/test_collection_service.py
tests/service/test_embedding_service.py
tests/util/__init__.py
embedin-0.2.1.dist-info/LICENSE
embedin-0.2.1.dist-info/METADATA
embedin-0.2.1.dist-info/WHEEL
embedin-0.2.1.dist-info/top_level.txt
embedin-0.2.1.dist-info/RECORD
