Metadata-Version: 2.1
Name: embedin
Version: 0.2.1
Summary: A lightweight vector database
Home-page: https://github.com/EmbedInAI/EmbedInDB
Author: EmbedInAI
Author-email: EmbedInAI@gmail.com
Classifier: Programming Language :: Python :: 3
Classifier: License :: OSI Approved :: Apache Software License
Classifier: Operating System :: OS Independent
Requires-Python: >=3.6
License-File: LICENSE
Requires-Dist: numpy (>=1.10.0)
Requires-Dist: hnswlib-embedinai (>=0.7.1)
Requires-Dist: sentence-transformers (>=2.2.2)
Requires-Dist: sqlalchemy (>=1.4.25)
Requires-Dist: psycopg2 (>=2.8.6)
Requires-Dist: pymysql (>=1.0.2)
Requires-Dist: pymssql (>=2.2.7)
Requires-Dist: faiss-cpu (>=1.7.4)
Requires-Dist: openai (>=0.27.6)
Requires-Dist: tqdm
